LICENSE
README.rst
setup.py
sharedmock/__init__.py
sharedmock/asserters.py
sharedmock/mock.py
sharedmock.egg-info/PKG-INFO
sharedmock.egg-info/SOURCES.txt
sharedmock.egg-info/dependency_links.txt
sharedmock.egg-info/requires.txt
sharedmock.egg-info/top_level.txt