Metadata-Version: 2.1
Name: sharedmock
Version: 0.1.0
Summary: A multiprocessing-friendly Python mock object
Home-page: https://github.com/elritsch/python-sharedmock
Author: Elmar Ritsch
Author-email: elmar.ritsch@gmail.com
License: Apache v2.0
Keywords: testing multiprocessing development
Classifier: Development Status :: 3 - Alpha
Classifier: Intended Audience :: Developers
Classifier: Topic :: Software Development :: Testing
Classifier: License :: OSI Approved :: Apache Software License
Classifier: Programming Language :: Python :: 3.5
License-File: LICENSE
Provides-Extra: test
Requires-Dist: coveralls==1.1; extra == "test"
Requires-Dist: prospector==0.12.4; extra == "test"
Requires-Dist: pylint==1.6.5; extra == "test"
Requires-Dist: pytest==3.0.5; extra == "test"
Requires-Dist: pytest-cov==2.4.0; extra == "test"
